[
    {
        "id": 2531118,
        "project_id": 1595,
        "action_name": "commented on",
        "target_id": 2281592,
        "target_iid": 2281592,
        "target_type": "Note",
        "author_id": 126,
        "target_title": "setting to disable notifications",
        "created_at": "2024-11-20T22:53:12.608Z",
        "note": {
            "id": 2281592,
            "type": null,
            "body": "Hi, screenshots in GNOME have nothing to with `gnome-screenshot` unless you have that application installed and actively open it.\n\nFeel free to file a ticket under `gnome-shell` but please always provide clear steps to reproduce, version information, distribution information. Thanks.",
            "attachment": null,
            "author": {
                "id": 126,
                "username": "aklapper",
                "name": "Andre Klapper",
                "state": "active",
                "locked": false,
                "avatar_url": "https://gitlab.gnome.org/uploads/-/system/user/avatar/126/avatar.png",
                "web_url": "https://gitlab.gnome.org/aklapper"
            },
            "created_at": "2024-11-20T22:53:11.763Z",
            "updated_at": "2024-11-20T22:55:12.778Z",
            "system": false,
            "noteable_id": 210851,
            "noteable_type": "Issue",
            "project_id": 1595,
            "resolvable": false,
            "confidential": false,
            "internal": false,
            "imported": false,
            "imported_from": "none",
            "noteable_iid": 256,
            "commands_changes": {}
        },
        "author": {
            "id": 126,
            "username": "aklapper",
            "name": "Andre Klapper",
            "state": "active",
            "locked": false,
            "avatar_url": "https://gitlab.gnome.org/uploads/-/system/user/avatar/126/avatar.png",
            "web_url": "https://gitlab.gnome.org/aklapper"
        },
        "imported": false,
        "imported_from": "none",
        "author_username": "aklapper"
    },
    {
        "id": 2531117,
        "project_id": 1595,
        "action_name": "closed",
        "target_id": 210851,
        "target_iid": 256,
        "target_type": "Issue",
        "author_id": 126,
        "target_title": "setting to disable notifications",
        "created_at": "2024-11-20T22:53:12.230Z",
        "author": {
            "id": 126,
            "username": "aklapper",
            "name": "Andre Klapper",
            "state": "active",
            "locked": false,
            "avatar_url": "https://gitlab.gnome.org/uploads/-/system/user/avatar/126/avatar.png",
            "web_url": "https://gitlab.gnome.org/aklapper"
        },
        "imported": false,
        "imported_from": "none",
        "author_username": "aklapper"
    },
    {
        "id": 2531116,
        "project_id": 1595,
        "action_name": "opened",
        "target_id": 210851,
        "target_iid": 256,
        "target_type": "Issue",
        "author_id": 68941,
        "target_title": "setting to disable notifications",
        "created_at": "2024-11-20T22:50:56.886Z",
        "author": {
            "id": 68941,
            "username": "trav9000",
            "name": "trav",
            "state": "active",
            "locked": false,
            "avatar_url": "https://secure.gravatar.com/avatar/48b82e4ed416f602d30d5c4b43eaeb86f13c7a003deee199672b84abc7a502af?s=80&d=identicon",
            "web_url": "https://gitlab.gnome.org/trav9000"
        },
        "imported": false,
        "imported_from": "none",
        "author_username": "trav9000"
    },
    {
        "id": 2525189,
        "project_id": 1595,
        "action_name": "commented on",
        "target_id": 2276003,
        "target_iid": 2276003,
        "target_type": "Note",
        "author_id": 149414,
        "target_title": "[FR] add tool to Simple edit screenshot",
        "created_at": "2024-11-14T21:10:13.721Z",
        "note": {
            "id": 2276003,
            "type": null,
            "body": "Hi,\nI'm also interested in a small set of edit functionalities. E.g:\n\n1. Drawing arrows / lines / rectangles / circles\n2. Textmarking\n3. Adding text, speech bubbles\n4. blurring / drawing filled rectangles\n5. ...\n\nI had a quick look at the codebase and I think it should be possible to add some of that functionality in a small integrated editor. The above features are my wishlist, number one being the one I miss the most.\n\nAnyone else interested in that?\nI'm currently considering implementing (or at least starting) that feature myself over the Christmas period this year if this feature is desired.",
            "attachment": null,
            "author": {
                "id": 149414,
                "username": "mhu",
                "name": "Mario H\u00fcttel",
                "state": "active",
                "locked": false,
                "avatar_url": "https://secure.gravatar.com/avatar/f0a1f1e04bf05e605530da731d4cd427f072e75e946e83e791a524330bf9f427?s=80&d=identicon",
                "web_url": "https://gitlab.gnome.org/mhu"
            },
            "created_at": "2024-11-14T21:10:13.045Z",
            "updated_at": "2024-11-14T21:23:55.403Z",
            "system": false,
            "noteable_id": 178050,
            "noteable_type": "Issue",
            "project_id": 1595,
            "resolvable": false,
            "confidential": false,
            "internal": false,
            "imported": false,
            "imported_from": "none",
            "noteable_iid": 233,
            "commands_changes": {}
        },
        "author": {
            "id": 149414,
            "username": "mhu",
            "name": "Mario H\u00fcttel",
            "state": "active",
            "locked": false,
            "avatar_url": "https://secure.gravatar.com/avatar/f0a1f1e04bf05e605530da731d4cd427f072e75e946e83e791a524330bf9f427?s=80&d=identicon",
            "web_url": "https://gitlab.gnome.org/mhu"
        },
        "imported": false,
        "imported_from": "none",
        "author_username": "mhu"
    },
    {
        "id": 2525164,
        "project_id": 1595,
        "action_name": "opened",
        "target_id": 210476,
        "target_iid": 255,
        "target_type": "Issue",
        "author_id": 149413,
        "target_title": "JS ERROR: Error: Expected type string for argument 'path' but got type undefined",
        "created_at": "2024-11-14T20:45:47.175Z",
        "author": {
            "id": 149413,
            "username": "wbruno512",
            "name": "Bruno Willy Zanqueta",
            "state": "active",
            "locked": false,
            "avatar_url": "https://secure.gravatar.com/avatar/2f6a4590e56fd4c006fe926e3ec59e1353d198d53484cb7cda6d49f918aca269?s=80&d=identicon",
            "web_url": "https://gitlab.gnome.org/wbruno512"
        },
        "imported": false,
        "imported_from": "none",
        "author_username": "wbruno512"
    },
    {
        "id": 2509120,
        "project_id": 1595,
        "action_name": "closed",
        "target_id": 209477,
        "target_iid": 254,
        "target_type": "Issue",
        "author_id": 148220,
        "target_title": "record mouse pointer by default",
        "created_at": "2024-10-31T00:25:17.273Z",
        "author": {
            "id": 148220,
            "username": "lu4p",
            "name": "Paul Scheduikat",
            "state": "active",
            "locked": false,
            "avatar_url": "https://secure.gravatar.com/avatar/f0152300c55e39b119642b88da9c203b74d6b38911e803931474bbdad63a87f7?s=80&d=identicon",
            "web_url": "https://gitlab.gnome.org/lu4p"
        },
        "imported": false,
        "imported_from": "none",
        "author_username": "lu4p"
    },
    {
        "id": 2509113,
        "project_id": 1595,
        "action_name": "opened",
        "target_id": 209477,
        "target_iid": 254,
        "target_type": "Issue",
        "author_id": 148220,
        "target_title": "record mouse pointer by default",
        "created_at": "2024-10-31T00:13:03.090Z",
        "author": {
            "id": 148220,
            "username": "lu4p",
            "name": "Paul Scheduikat",
            "state": "active",
            "locked": false,
            "avatar_url": "https://secure.gravatar.com/avatar/f0152300c55e39b119642b88da9c203b74d6b38911e803931474bbdad63a87f7?s=80&d=identicon",
            "web_url": "https://gitlab.gnome.org/lu4p"
        },
        "imported": false,
        "imported_from": "none",
        "author_username": "lu4p"
    },
    {
        "id": 2500625,
        "project_id": 1595,
        "action_name": "commented on",
        "target_id": 2254274,
        "target_iid": 2254274,
        "target_type": "Note",
        "author_id": 145841,
        "target_title": "All instances of program are closed when clicking \"cancel\" in one of them",
        "created_at": "2024-10-21T19:24:22.487Z",
        "note": {
            "id": 2254274,
            "type": null,
            "body": "Sorry, I thought this would be an easy one to reproduce ;)\n\nI'm using gnome-screenshot 41.0 on Mint 22 Cinnamon.",
            "attachment": null,
            "author": {
                "id": 145841,
                "username": "returndanilo",
                "name": "Danilo Rezende",
                "state": "active",
                "locked": false,
                "avatar_url": "https://secure.gravatar.com/avatar/bcd07f2d49866af38d31e8da274f61127dea978ba1dc273350a1f753dc99fb5b?s=80&d=identicon",
                "web_url": "https://gitlab.gnome.org/returndanilo"
            },
            "created_at": "2024-10-21T19:24:21.878Z",
            "updated_at": "2024-10-21T19:24:21.878Z",
            "system": false,
            "noteable_id": 208944,
            "noteable_type": "Issue",
            "project_id": 1595,
            "resolvable": false,
            "confidential": false,
            "internal": false,
            "imported": false,
            "imported_from": "none",
            "noteable_iid": 252,
            "commands_changes": {}
        },
        "author": {
            "id": 145841,
            "username": "returndanilo",
            "name": "Danilo Rezende",
            "state": "active",
            "locked": false,
            "avatar_url": "https://secure.gravatar.com/avatar/bcd07f2d49866af38d31e8da274f61127dea978ba1dc273350a1f753dc99fb5b?s=80&d=identicon",
            "web_url": "https://gitlab.gnome.org/returndanilo"
        },
        "imported": false,
        "imported_from": "none",
        "author_username": "returndanilo"
    },
    {
        "id": 2500295,
        "project_id": 1595,
        "action_name": "commented on",
        "target_id": 2254029,
        "target_iid": 2254029,
        "target_type": "Note",
        "author_id": 126,
        "target_title": "Cannot save as jxl on asahi linux",
        "created_at": "2024-10-21T14:23:49.016Z",
        "note": {
            "id": 2254029,
            "type": null,
            "body": "What it says:\n\n> `** (gnome-screenshot:12809): CRITICAL **: 06:49:29.848: Unable to save the screenshot: This build of gdk-pixbuf does not support saving the image format: jxl`",
            "attachment": null,
            "author": {
                "id": 126,
                "username": "aklapper",
                "name": "Andre Klapper",
                "state": "active",
                "locked": false,
                "avatar_url": "https://gitlab.gnome.org/uploads/-/system/user/avatar/126/avatar.png",
                "web_url": "https://gitlab.gnome.org/aklapper"
            },
            "created_at": "2024-10-21T14:23:48.375Z",
            "updated_at": "2024-10-21T14:23:48.375Z",
            "system": false,
            "noteable_id": 208969,
            "noteable_type": "Issue",
            "project_id": 1595,
            "resolvable": false,
            "confidential": false,
            "internal": false,
            "imported": false,
            "imported_from": "none",
            "noteable_iid": 253,
            "commands_changes": {}
        },
        "author": {
            "id": 126,
            "username": "aklapper",
            "name": "Andre Klapper",
            "state": "active",
            "locked": false,
            "avatar_url": "https://gitlab.gnome.org/uploads/-/system/user/avatar/126/avatar.png",
            "web_url": "https://gitlab.gnome.org/aklapper"
        },
        "imported": false,
        "imported_from": "none",
        "author_username": "aklapper"
    },
    {
        "id": 2500294,
        "project_id": 1595,
        "action_name": "closed",
        "target_id": 208969,
        "target_iid": 253,
        "target_type": "Issue",
        "author_id": 126,
        "target_title": "Cannot save as jxl on asahi linux",
        "created_at": "2024-10-21T14:23:48.886Z",
        "author": {
            "id": 126,
            "username": "aklapper",
            "name": "Andre Klapper",
            "state": "active",
            "locked": false,
            "avatar_url": "https://gitlab.gnome.org/uploads/-/system/user/avatar/126/avatar.png",
            "web_url": "https://gitlab.gnome.org/aklapper"
        },
        "imported": false,
        "imported_from": "none",
        "author_username": "aklapper"
    },
    {
        "id": 2500264,
        "project_id": 1595,
        "action_name": "opened",
        "target_id": 208969,
        "target_iid": 253,
        "target_type": "Issue",
        "author_id": 146968,
        "target_title": "Cannot save as jxl on asahi linux",
        "created_at": "2024-10-21T14:01:03.447Z",
        "author": {
            "id": 146968,
            "username": "simplycorbett",
            "name": "Tyler S",
            "state": "active",
            "locked": false,
            "avatar_url": "https://secure.gravatar.com/avatar/567e5a7fc88bb041cfcb9354c6e2aa0b55bb3f0c436b16e210c8a2866910df35?s=80&d=identicon",
            "web_url": "https://gitlab.gnome.org/simplycorbett"
        },
        "imported": false,
        "imported_from": "none",
        "author_username": "simplycorbett"
    },
    {
        "id": 2499979,
        "project_id": 1595,
        "action_name": "commented on",
        "target_id": 2253755,
        "target_iid": 2253755,
        "target_type": "Note",
        "author_id": 126,
        "target_title": "All instances of program are closed when clicking \"cancel\" in one of them",
        "created_at": "2024-10-21T10:08:00.797Z",
        "note": {
            "id": 2253755,
            "type": null,
            "body": "Hi @returndanilo, thanks for taking the time to report this. Please always provide the exact version of the application and distribution/operating system information when reporting an issue. Thanks!",
            "attachment": null,
            "author": {
                "id": 126,
                "username": "aklapper",
                "name": "Andre Klapper",
                "state": "active",
                "locked": false,
                "avatar_url": "https://gitlab.gnome.org/uploads/-/system/user/avatar/126/avatar.png",
                "web_url": "https://gitlab.gnome.org/aklapper"
            },
            "created_at": "2024-10-21T10:08:00.072Z",
            "updated_at": "2024-10-21T10:08:00.072Z",
            "system": false,
            "noteable_id": 208944,
            "noteable_type": "Issue",
            "project_id": 1595,
            "resolvable": false,
            "confidential": false,
            "internal": false,
            "imported": false,
            "imported_from": "none",
            "noteable_iid": 252,
            "commands_changes": {}
        },
        "author": {
            "id": 126,
            "username": "aklapper",
            "name": "Andre Klapper",
            "state": "active",
            "locked": false,
            "avatar_url": "https://gitlab.gnome.org/uploads/-/system/user/avatar/126/avatar.png",
            "web_url": "https://gitlab.gnome.org/aklapper"
        },
        "imported": false,
        "imported_from": "none",
        "author_username": "aklapper"
    },
    {
        "id": 2499747,
        "project_id": 1595,
        "action_name": "opened",
        "target_id": 208944,
        "target_iid": 252,
        "target_type": "Issue",
        "author_id": 145841,
        "target_title": "All instances of program are closed when clicking \"cancel\" in one of them",
        "created_at": "2024-10-21T04:21:17.900Z",
        "author": {
            "id": 145841,
            "username": "returndanilo",
            "name": "Danilo Rezende",
            "state": "active",
            "locked": false,
            "avatar_url": "https://secure.gravatar.com/avatar/bcd07f2d49866af38d31e8da274f61127dea978ba1dc273350a1f753dc99fb5b?s=80&d=identicon",
            "web_url": "https://gitlab.gnome.org/returndanilo"
        },
        "imported": false,
        "imported_from": "none",
        "author_username": "returndanilo"
    }
]